LICENSE
MANIFEST.in
README.md
VERSION
setup.py
docker_sand.egg-info/PKG-INFO
docker_sand.egg-info/SOURCES.txt
docker_sand.egg-info/dependency_links.txt
docker_sand.egg-info/entry_points.txt
docker_sand.egg-info/requires.txt
docker_sand.egg-info/top_level.txt
sand/__init__.py
sand/sand.py
sand/internal/__init__.py
sand/internal/docker_image.py
sand/internal/main.py
sand/internal/sandfile_watcher.py
sand/internal/sandfile_executor/__init__.py
sand/internal/sandfile_executor/commands.py
sand/internal/sandfile_executor/sandfile_executor.py